pip_remove/__init__.py
pip_remove/orphans.py
pip_remove/remove.py
pip_remove-0.1.0.dist-info/METADATA
pip_remove-0.1.0.dist-info/WHEEL
pip_remove-0.1.0.dist-info/entry_points.txt
pip_remove-0.1.0.dist-info/top_level.txt
pip_remove-0.1.0.dist-info/RECORD
