Metadata-Version: 2.4
Name: pip-remove
Version: 0.1.0
Summary: Removes both the specified package and its orphans from the current environment.
Author-email: Axis <blankRiot96@gmail.com>
License: MIT
Requires-Python: >=3.10
Requires-Dist: GitPython==3.1.44
Requires-Dist: rich==13.9.4
